experiment_utils/__init__.py
experiment_utils/entbal.py
experiment_utils/estimators.py
experiment_utils/experiment_analyzer.py
experiment_utils/power_sim.py
experiment_utils/utils.py
experiment_utils_pd-0.1.10.dist-info/licenses/LICENSE
experiment_utils_pd-0.1.10.dist-info/METADATA
experiment_utils_pd-0.1.10.dist-info/WHEEL
experiment_utils_pd-0.1.10.dist-info/top_level.txt
experiment_utils_pd-0.1.10.dist-info/RECORD
