Metadata-Version: 2.4
Name: experiment-utils-pd
Version: 0.1.10
Summary: Set of utility functions for analyzing experimental and observational data
Author-email: Sebastian Daza <sebastian.daza@gmail.com>
License: MIT License
Classifier: Programming Language :: Python :: 3
Classifier: License :: OSI Approved :: MIT License
Classifier: Operating System :: OS Independent
Classifier: Intended Audience :: Science/Research
Classifier: Topic :: Scientific/Engineering :: Information Analysis
Classifier: Development Status :: 3 - Alpha
Requires-Python: >=3.10
License-File: LICENSE
Requires-Dist: numpy>=1.21.5
Requires-Dist: pandas>=2.3.1
Requires-Dist: matplotlib>=3.5.2
Requires-Dist: seaborn>=0.11.2
Requires-Dist: multiprocess>=0.70.14
Requires-Dist: threadpoolctl>=3.5.0
Requires-Dist: statsmodels>=0.13.2
Requires-Dist: scipy>=1.9.1
Requires-Dist: linearmodels>=6.1
Requires-Dist: scikit-learn==1.5.2
Requires-Dist: xgboost>=2.1.3
Requires-Dist: pytest>=8.3.5
Requires-Dist: ruff>=0.11.7
Requires-Dist: ipykernel>=6.29.5
Requires-Dist: build>=1.3.0
Requires-Dist: twine>=6.1.0
Dynamic: license-file
